flask_mercadopago/__init__.py
flask_mercadopago/core.py
flask_mercadopago/utils.py
flask_mercadopago/static/js/mercadopago/v2.js
Flask_Mercadopago-1.0.0.dist-info/LICENSE
Flask_Mercadopago-1.0.0.dist-info/METADATA
Flask_Mercadopago-1.0.0.dist-info/WHEEL
Flask_Mercadopago-1.0.0.dist-info/top_level.txt
Flask_Mercadopago-1.0.0.dist-info/RECORD
