Metadata-Version: 2.1
Name: Flask-Mercadopago
Version: 1.0.0
Summary: Implementation of Mercado Pago OAuth in Flask.
Home-page: https://github.com/juniors90/Flask-Mercadopago
Author: Ferreira Juan David
Author-email: juandavid9a0@gmail.com
License: The MIT License
Project-URL: Source, https://github.com/juniors90/Flask-Mercadopago
Project-URL: Tracker, https://github.com/juniors90/Flask-Mercadopago/issues
Project-URL: Donate, https://www.paypal.com/donate?hosted_button_id=LFAQ7E7TJ4HSY
Project-URL: Funding, https://paypal.me/juniors90
Keywords: API,Flask,Mercado Pago
Platform: any
Classifier: Development Status :: 4 - Beta
Classifier: License :: OSI Approved :: MIT License
Classifier: Operating System :: OS Independent
Classifier: Programming Language :: Python
Classifier: Programming Language :: Python :: 3.8
Classifier: Topic :: Internet :: WWW/HTTP :: Dynamic Content
Classifier: Topic :: Software Development :: Libraries :: Python Modules
License-File: LICENSE
Requires-Dist: Flask (>=2.0.1)
Requires-Dist: requests (>=2.28.1)
Requires-Dist: Werkzeug (>=2.0.3)
Requires-Dist: mercadopago (>=2.2.0)
